pdal/__init__.py
pdal/drivers.py
pdal/libpdalpython.cpython-310-darwin.so
pdal/pipeline.py
pdal-3.2.2.dist-info/LICENSE.txt
pdal-3.2.2.dist-info/METADATA
pdal-3.2.2.dist-info/WHEEL
pdal-3.2.2.dist-info/top_level.txt
pdal-3.2.2.dist-info/RECORD
