Metadata-Version: 2.1
Name: pdal
Version: 3.2.2
Summary: Point cloud data processing
Home-page: https://pdal.io
Author: Howard Butler
Author-email: howard@hobu.co
Maintainer: Howard Butler
Maintainer-email: howard@hobu.co
License: BSD
Keywords: point cloud spatial
Classifier: Development Status :: 5 - Production/Stable
Classifier: Intended Audience :: Developers
Classifier: Intended Audience :: Science/Research
Classifier: License :: OSI Approved :: BSD License
Classifier: Operating System :: OS Independent
Classifier: Programming Language :: Python :: 3.7
Classifier: Programming Language :: Python :: 3.8
Classifier: Programming Language :: Python :: 3.9
Classifier: Programming Language :: Python :: 3.10
Classifier: Topic :: Scientific/Engineering :: GIS
License-File: LICENSE.txt
